accounting_vasco/__init__.py
accounting_vasco/builder.py
accounting_vasco/core.py
accounting_vasco/definitions.py
accounting_vasco-0.1.4.dist-info/licenses/LICENSE
accounting_vasco-0.1.4.dist-info/METADATA
accounting_vasco-0.1.4.dist-info/WHEEL
accounting_vasco-0.1.4.dist-info/top_level.txt
accounting_vasco-0.1.4.dist-info/RECORD
