Metadata-Version: 2.4
Name: accounting_vasco
Version: 0.1.4
Summary: Generate VASCO KN-21 XML export for accounting software 
Home-page: https://github.com/boris-savic/python-accounting-vasco
Download-URL: https://github.com/boris-savic/python-accounting-vasco/tarball/0.1.4
Author: Boris Savic
Author-email: boris70@gmail.com
Keywords: python vasco,accounting,vasco
License-File: LICENSE
Requires-Dist: lxml>=4.5.1
Requires-Dist: iso3166>=1.0.1
Dynamic: author
Dynamic: author-email
Dynamic: download-url
Dynamic: home-page
Dynamic: keywords
Dynamic: license-file
Dynamic: requires-dist
Dynamic: summary
